{
  "version": "2.0",
  "aion_dna": "2a22397d07c574b58c016fc43f4450479313a0c0d7d5eb9115233b0f1d579f3f",
  "execution_history": [
    {
      "id": "ALPHA-1754276825",
      "protocol": "ALPHA",
      "parameters": {
        "research_domain": "artificial_intelligence",
        "research_type": "exploratory",
        "seed_concepts": [
          "quantum_consciousness",
          "neuroplastic_systems"
        ]
      },
      "timestamp": "2025-08-03T21:07:06.321984",
      "execution_time": 0.0010142326354980469,
      "status": "success"
    },
    {
      "id": "BETA-1754276826",
      "protocol": "BETA",
      "parameters": {
        "app_name": "QuantumMind",
        "architecture": "flutter",
        "platforms": [
          "Android",
          "iOS"
        ]
      },
      "timestamp": "2025-08-03T21:07:06.322819",
      "execution_time": 0.0001628398895263672,
      "status": "success"
    },
    {
      "id": "GAMMA-1754276826",
      "protocol": "GAMMA",
      "parameters": {
        "project_name": "EnterpriseAI",
        "architecture": "microservices"
      },
      "timestamp": "2025-08-03T21:07:06.323488",
      "execution_time": 0.00014901161193847656,
      "status": "success"
    },
    {
      "id": "DELTA-1754276826",
      "protocol": "DELTA",
      "parameters": {
        "app_name": "AI Dashboard",
        "tech_stack": "next_js"
      },
      "timestamp": "2025-08-03T21:07:06.324196",
      "execution_time": 0.00016164779663085938,
      "status": "success"
    },
    {
      "id": "OMEGA-1754276826",
      "protocol": "OMEGA",
      "parameters": {
        "project_name": "AI License Manager",
        "action": "generate_license",
        "license_type": "COMMERCIAL_BASIC",
        "software_name": "QuantumMind Pro"
      },
      "timestamp": "2025-08-03T21:07:06.324911",
      "execution_time": 0.00018477439880371094,
      "status": "success"
    }
  ],
  "timestamp": "2025-08-03T21:07:06.325221"
}